tofipa/__init__.py
tofipa/_btclient.py
tofipa/_cli.py
tofipa/_combinator.py
tofipa/_config.py
tofipa/_errors.py
tofipa/_location.py
tofipa-0.4.4.dist-info/LICENSE
tofipa-0.4.4.dist-info/METADATA
tofipa-0.4.4.dist-info/WHEEL
tofipa-0.4.4.dist-info/entry_points.txt
tofipa-0.4.4.dist-info/top_level.txt
tofipa-0.4.4.dist-info/RECORD
