Metadata-Version: 2.1
Name: tofipa
Version: 0.4.4
Summary: Get download directory from torrent file
Home-page: https://codeberg.org/plotski/tofipa
Author: plotski
Author-email: plotski@example.org
Classifier: Programming Language :: Python :: 3.8
Classifier: Programming Language :: Python :: 3.9
Classifier: Programming Language :: Python :: 3.10
Classifier: License :: OSI Approved :: GNU General Public License v3 or later (GPLv3+)
Requires-Python: >=3.8
License-File: LICENSE
Requires-Dist: aiobtclientapi (==1.*)
Requires-Dist: pyxdg (==0.*)
Requires-Dist: torf (==4.*)
